doc_analytics/__init__.py
doc_analytics/collections.py
doc_analytics/doc_organizer.py
doc_analytics/document.py
doc_analytics/search.py
doc_analytics/utils.py
document_basics-0.1.1.dist-info/METADATA
document_basics-0.1.1.dist-info/WHEEL
document_basics-0.1.1.dist-info/top_level.txt
document_basics-0.1.1.dist-info/RECORD
