Metadata-Version: 2.4
Name: document-basics
Version: 0.1.1
Summary: Add your description here
Requires-Python: >=3.13
Requires-Dist: attrs>=25.3.0
Requires-Dist: networkx[default]>=3.4.2
Requires-Dist: pydantic>=2.11.4
Requires-Dist: scikit-learn>=1.6.1
Requires-Dist: structlog>=25.3.0
